{
  "HOME": [ "Home", "หน้าแรก" ],
  "AIR_TICKET": [ "Air Ticket", "ตั๋วเครื่องบิน" ],
  "DEALS": [ "Deals", "ดีล" ],
  "ABOUT_US": [ "About Us", "เกี่ยวกับเรา" ],
  "FIND_TRIP": [ "Find Trip", "ค้นหาเที่ยวบิน" ],
  "ROUNDTRIP": [ "Roundtrip", "ไป-กลับ" ],
  "ONEWAY": [ "Oneway", "เที่ยวเดียว" ],
  "ORIGIN": [ "Origin", "เมืองต้นทาง" ],
  "DESTINATION": [ "Destination", "เมืองปลายทาง" ],
  "DEFINE_ORIGIN": [ "Origin", "ระบุเมืองต้นทาง" ],
  "DEFINE_DESTINATION": [ "Destination", "ระบุเมืองปลายทาง" ],
  "BKK_DEFAULT": [ "Bangkok[BKK] - Thailand", "กรุงเทพ[BKK] - ไทย" ],
  "DEPARTING": [ "Departing", "วันเดินทางไป" ],
  "RETURNING": [ "Returning", "วันเดินทางกลับ" ],
  "TRAVELERS": [ "Travelers", "ผู้โดยสาร" ],
  "PASSENGERS": [ "Passengers", "ผู้โดยสาร" ],
  "CLASS": [ "Class", "ชั้นโดยสาร" ],
  "ECONOMY": [ "Ecomomy", "ชั้นประหยัด" ],
  "PREMIUM_ECONOMY": [ "Premium Ecomomy", "ชั้นประหยัดพรีเมี่ยม" ],
  "BUSINESS": [ "Business", "ชั้นธุรกิจ" ],
  "FIRST": [ "First", "ชั้นหนึ่ง" ],
  "ADULTS": [ "Adults", "ผู้ใหญ่" ],
  "ADULT": [ "Adult", "ผู้ใหญ่" ],
  "CHILD": [ "Child", "เด็ก" ],
  "CHILDREN": [ "Children", "เด็ก" ],
  "INFANTS": [ "Infants", "ทารก" ],
  "INFANT": [ "Infant", "ทารก" ],
  "AGE": [ "Age", "อายุ" ],
  "YEARS": [ "Years", "ปี" ],
  "PRICE_INFO": [ "This is prices, included fuel and airport taxes. Food and baggage allowance for full servic airlines are up to airline's conditions.", "ราคารวมภาษีน้ำมัน, สนามบินแล้ว ในสายการบินฟูลเซอร์วิสจะรวมอาหาร+น้ำหนักสัมภาระตามเงื่อนไข (ถ้ามี) " ],
  "TOTAL": [ "Total", "รวม" ],
  "DIRECT_FLIGHT": [ "Direct", "บินตรง" ],
  "STOPS": [ "Stops", "จุดแวะพัก" ],
  "HRS": [ "Hrs", "ช.ม." ],
  "MINS": [ "Mins", "น." ],
  "DEPARTURE_FLIGHT": [ "Departure flight", "เที่ยวบินขาไป" ],
  "RETURN_FLIGHT": [ "Return flight", "เที่ยวบินขากลับ" ],
  "TOTAL_TIME": [ "Total time", "เวลารวม" ],
  "STOPON": [ "Stop", "แวะพัก" ],
  "FILTER": [ "Filter", "ตัวกรอง" ],
  "AIRLINES": [ "Airlines", "สายการบิน" ],
  "PRICE": [ "Price", "ราคา" ],
  "NO_STOP": [ "Nonstop", "ไม่แวะพัก" ],
  "STOP_POINT": [ "Stops", "จุดแวะพัก" ],
  "DEPARTURE_TIME": [ "Departure Time", "เวลาออกเดินทาง" ],
  "RETURN_TIME": [ "Return Time", "เวลาเดินทางกลับ" ],
  "BOOK_NOW": [ "Book Now", "จองเลย" ],
  "PLEASE_SELECT_DEP": [ "Please select departure flight", "กรุณาเลือกเที่ยวบินขาไป" ],
  "PLEASE_SELECT_RET": [ "Please select return flight", "กรุณาเลือกเที่ยวบินขากลับ" ],
  "YOUR_TRIP": [ "Your Trip", "การเดินทางของคุณ" ],
  "OPERATED_BY": [ "Operated by", "บินโดย" ],
  "FARE_DETAIL": [ "Fare Details", "รายละเอียดการชำระเงิน" ],
  "PAX_NO": [ "Paseenger No.", "ผู้โดยสารคนที่" ],
  "TAX": [ "Tax", "ภาษี" ],
  "GRAND_TOTAL": [ "Grand total", "รวมทั้งหมด" ],
  "PAX_DETAIL": [ "Passengers Detail", "รายละเอียดผู้โดยสาร" ],
  "PAX_NAME_WARNING": [
    "Passenger name must be <span style='color: #ff0000'><u>English</u></span> and <u>same as your passport</u>!",
    "ชื่อผู้โดยสารต้องเป็น<span style='color: #ff0000'><u>ภาษาอังกฤษ</u></span> และต้องมั่นใจว่า <u>ตรงกับข้อมูลในพาสปอร์ต</u>ด้วยนะ อันนี้สำคัญมาก!"
  ],
  "OPTIONAL": [ "Optional", "ถ้าไม่มีไม่ต้องใส่" ],
  "TITLE": [ "Title", "คำนำหน้า" ],
  "FIRSTNAME": [ "First Name", "ชื่อจริง" ],
  "MIDDLENAME": [ "Middle Name", "ชื่อกลาง" ],
  "LASTNAME": [ "Last Name", "นามสกุล" ],
  "EMAIL": [ "Email", "อีเมล" ],
  "TELNO": [ "Tel No.", "เบอร์โทรศัพท์" ],
  "BIRTHDAY": [ "Birthday", "วัน/เดือน/ปีเกิด" ],
  "FARE_CONDITION": [ "Fare Condition", "เงื่อนไขบัตรโดยสาร" ],
  "FARE_CONDITION_DETAIL": [
    "<b>We will use contions same as airlines</b> Anyway, if the fare conditions of deparure flights are different from return flights, we will use the contions of the lowest fare to issue tickets. You can ask the details at Line id @Gogojii",
    "<b>ทางบริษัทจะยึดเงื่อนไขบัตรโดยสารเดียวกันกับสายการบินเป็นหลัก</b>  ทั้งนี้ หากประเภทบัตรโดยสารของเที่ยวบินขาไปและขากลับที่เลือกจองมีความแตกต่างกัน จะยึดเงื่อนไขของบัตรโดยสารที่ราคาต่ำกว่าในการออกบัตรโดยสาร สอบถามรายละเอียดเพิ่มที่ไลน์ไอดี @Gogojii"
  ],
  "I_AGREE": [ "I have read and agree the fare conditions.", "ข้าพเจ้าได้อ่านและยอมรับเงื่อนไขบัตรโดยสาร" ],
  "FLIGHTNOTFOUND": [ "Flights not found", "ไม่พบเที่ยวบินที่คุณต้องการ" ],
  "TIMEOUT": [ "System time out", "ระบบหมดเวลา" ],
  "MORE_INFO": [ "This flight cannot reserve.<br> Please contact Gogojii for information, Tel. 02-0263474 Working Hours: 09.00 - 18.00 or LINE ID: @Gogojii", "เที่ยวบินนี้ไม่สามารถทำการจองได้<br> กรุณาติดต่อกวิ้นเพื่อตรวจสอบ เบอร์โทร 02-0263474 เวลาทำการ 09.00 - 18.00 น. หรือผ่านไลน์แอด @Gogojii" ],
  "SEARCH_AGAIN": [ "Search Again", "ค้นหาอีกครั้ง" ],
  "PLEASE_AGREE": [ "Please indicate that you have read and agree to the Fare Conditions", "กรุณายอมรับเงื่อนไขการออกบัตรโดยสาร" ],
  "BOOKING_COMPLETE": [ "Booking Complete!", "จองสำเร็จ!" ],
  "BOOKING_SUMMARY_1": [ "The reservation has been completed. We will send the e-ticket to ", "ระบบทำการสำรองที่นั่งเรียบร้อยแล้ว เราจะทำการส่งตั๋วเครื่องบิน (e-ticket) ไปยังอีเมล" ],
  "BOOKING_SUMMARY_2": [ " after the payment has been verfied.", "หลังจากการตรวจสอบการชำระเงินเรียบร้อยแล้ว" ],
  "BOOKING_REF": [ "Booking Ref.", "เลขที่อ้างอิงการจอง" ],
  "STATUS": [ "Status", "สถานะ" ],
  "WAITING_PAY": [ "Waing for payment", "รอการชำระเงิน" ],
  "PAID_BEFORE": [ "Paid before", "ชำระเงินก่อนวันที่" ],
  "CONTACT": [ "Contact", "ติดต่อ" ],
  "ALL_AIRLINE": [ "All Airlines", "ทุกสายการบิน" ],
  "SHOW_OPTION": [ "Show options", "แสดงตัวเลือก" ],
  "HIDE_OPTION": [ "Hide options", "ซ่อนตัวเลือก" ],
  "LAST_SEATS": [ "last seats", "ที่นั่งสุดท้าย" ],
  "PLEASE_SELECT_PAYMENT_METHOD": [ "Please select payment method", "กรุณาเลือกวิธีชำระเงิน" ],
  "PAY_NOW": [ "Pay now", "ชำระทันที" ],
  "GUARANTEE_PRICE_MESSAGE": [ "To guarantee this price, please pay now with Credit card or Paypal account", "เพื่อยืนยันราคานี้ ชำระด้วยบัตรเครดิตหรือบัญชี Paypal ได้ทันที" ],
  "CREDIT_DEBIT_CARD": [ "Credit/Debit Card", "บัตรเครดิต/เดบิต" ],
  "FEE": [ "Fee", "ค่าธรรมเนียม" ],
  "PAYMENT_AMOUNT": [ "Payment amount", "ยอดที่ต้องชำระ" ],
  "PAY_LATER": [ "Pay later", "ชำระภายหลัง" ],
  "PRICE_MAY_CHANGE_MESSAGE": [ "Don't miss! Price may be changed", "อย่ามัวลังเล! ราคาอาจจะมีการเปลี่ยนแปลงนะ" ],
  "COUNTER_SERVICE": [ "Counter Service", "เคาน์เตอร์เซอร์วิส" ],
  "BANK_TRANSFER": [ "Bank Transfer", "โอนเงิน" ],
  "NO_FEE": [ "Free! No service fee", "ฟรี! ไม่มีค่าธรรมเนียม" ],
  "BANK_TRANSFER_MSG_1": [
    "Booking confirmation and bank accounts information have been sent to email",
    "รายละเอียดยืนยันการจองและข้อมูลบัญชีธนาคารถูกส่วไปที่ อีเมล"
  ],
  "BANK_TRANSFER_MSG_2": [ "", "เรียบร้อยแล้ว" ],
  "PLEASE_PAY_BEFORE": [ "Please pay and send the slip to us before", "กรุณาชำระและส่งหลักฐานการโอนเงิน ภายใน" ],
  "KBANK_TITLE": [ "Kasikorn Bank / Central Pinklao Branch", "ธนาคารกสิกรไทย สาขาเซ็นทรัล ปิ่นเกล้า" ],
  "KTB_TITLE": [ "Krungthai Bank / Software Park Branch", "ธนาคารกรุงไทย สาขาซอฟต์แวร์ปาร์ค" ],
  "ACCOUNT_NAME": [ "Account Name: Asia One Click Co., Ltd.", "บริษัท เอเชีย วัน คลิก จำกัด" ],
  "ACCOUNT_NO": [ "Account No.", "เลขที่บัญชี" ],
  "PAY": [ "Pay", "ดำเนินการชำระเงิน" ],
  "BOOKING_COMPLETE_HEAD": [ "Booking Complete!", "จองสำเร็จแล้ว!" ],
  "CS_MESSAGE": [ "I've sent your payslip to your e-mail, plese make a payment before expired date.", "กวิ้นส่งใบ Pay in ไปที่อีเมลของคุณเรียบร้อยแล้ว" ],
  "CS_MESSAGE_1": [ "Please check your email inbox or junk mail", "กรุณาตรวจสอบกล่อง Inbox รวมทั้ง Junk mail ของท่าน" ],
  "CS_MESSAGE_2": [ "Bring Pay in slip to Counter Service for paid", "นำใบ Pay in ไปแสดงและชำระเงินได้ที่เคาน์เตอร์เซอร์วิสทุกสาขาใกล้บ้านคุณได้เลย" ],
  "CS_MESSAGE_3": [ "After we check your payment, we will send E-ticket to your email", "รอกวิ้นตรวจสอบหลักฐานการชำระเงิน และส่งบัตรโดยสาร [E-Ticket] ไปทางอีเมล" ],
  "PLEASE_CHECK_MAIL": [ "'GuinT has already sent the payment detail to your email", "กวิ้นจัดส่งรายละเอียดการชำระเงินไปทางอีเมลเรียบร้อยแล้ว" ],
  "CHECK_MAIL_1": [ "Please check your email inbox or junk mail", "กรุณาตรวจสอบกล่อง Inbox รวมทั้ง Junk mail ของท่าน" ],
  "CHECK_MAIL_2": [ "Make a payment", "ดำเนินการชำระเงิน" ],
  "CHECK_MAIL_3": [ "Inform the payment slip to us before the deadline", "แจ้งหลักฐานชำระเงินภายในระยะเวลากำหนด" ],
  "CHECK_MAIL_4": [ "After we check your payment, we will send E-ticket to your email", "รอกวิ้นตรวจสอบหลักฐานการชำระเงิน และส่งบัตรโดยสาร [E-Ticket] ไปทางอีเมล" ],
  "SELECT_DEPARTURE_FLIGHT": [ "Please Select Departure Flight", "เลือกเที่ยวบินขาไป" ],
  "SELECT_RETURN_FLIGHT": [ "Please Select Return Flight", "เลือกเที่ยวบินขากลับ" ],
  "FLIGHTINDEX": [ "Flight", "เที่ยวบินที่" ],
  "AVAIL_SEAT": [ "Avail. Seat", "ที่นั่งว่าง" ],
  "TOTAL_TRAVEL_TIME": [ "Total travel time", "ระยะเวลาในการเดินทางทั้งหมด" ],
  "BAGGAAGE_UNIT_N": [ "pcs", "ใบ" ],
  "BAGGAAGE_UNIT_700": [ "KG", "กก." ],
  "BAGGAAGE_UNIT_701": [ "LB", "ปอนด์" ],
  "SHOW_FLIGHT_DETIAL": [ "Show flight detials", "แสดงรายละเอียดเที่ยวบิน" ],
  "HIDE_FLIGHT_DETIAL": [ "Hide flight detials", "ซ่อนรายละเอียดเที่ยวบิน" ],
  "DISMISS": [ "Dismiss", "ตกลง" ],
  "WAITAMINUTE": [ "Wait a minute", "เดี๋ยวก่อน" ],
  "PRICECHANGE1": [ "Price has been change from ", "ราคามีการเปลี่ยนแปลงจาก " ],
  "PRICECHANGE2": [ " baht to ", " บาท เป็น " ],
  "PRICECHANGE3": [ " baht.", " บาท" ],
  "PRICECHANGE4": [ "Since the fuel tax has been changed.", "เนื่องจากภาษีน้ำมันมีการเปลี่ยนแปลง" ],
  "GUINT_HERO": [ "Choose the 'Guint Hero Services", "เลือกรับบริการ \"กวิ้นฮีโร่\"" ],
  "FREE": [ "Free", "ฟรี" ],
  "GUINT_ALERT": [ "'Guint Alert", "กวิ้น Alert" ],
  "GUINT_ALERT_DETAIL": [ "Inform you when your flight was changed or cancelled", "แจ้งให้ทราบเมื่อเที่ยวบินถูกยกเลิกหรือเปลี่ยนแปลง" ],
  "GUINT_TAKE_CARE": [ "'Guint Take Care", "กวิ้น Take Care" ],
  "GUINT_TAKE_CARE_DETAIL": [ "Take care you since departure until back to home", "ดูแลคุณตั้งแต่เริ่มเดินทางจนถึงวันกลับบ้าน" ],
  "NAME": [ "Name", "ชื่อ-นามสกุล" ],
  "SHOW_ALL": [ "Show all", "แสดงผลลัพธ์ทั้งหมด" ],
  "SHOW_LESS": [ "Show less", "แสดงผลลัพธ์ให้น้อยลง" ],
  "PRICE_START_FROM": [ "Price start from ", "ราคาเริ่มต้นที่" ],
  "BAHT/PAX": [ "Baht per peson", "บาท/ท่าน" ],
  "APPLY": [ "Apply", "ยืนยัน" ],
  "BOOK_NOW_PAY_LATER": [ "Book now, Pay late", "จองเลย ยังไม่ต้องจ่าย" ],
  "CHANGE_SEARCH": [ "Change search", "เปลี่ยนการค้นหา" ]
}
